ace/__init__.py
ace/config.py
ace/agents/__init__.py
ace/agents/openai_agents.py
ace/core/__init__.py
ace/core/curator.py
ace/core/interfaces.py
ace/core/reflector.py
ace/storage/__init__.py
ace/storage/embedder.py
ace/storage/faiss_index.py
ace/storage/sqlite_storage.py
agentic_context_engineering-1.1.1.dist-info/METADATA
agentic_context_engineering-1.1.1.dist-info/WHEEL
agentic_context_engineering-1.1.1.dist-info/licenses/LICENSE
agentic_context_engineering-1.1.1.dist-info/RECORD
