Metadata-Version: 2.4
Name: agentic-context-engineering
Version: 1.1.1
Summary: Agentic Context Engineering utilities for OpenAI Agents.
Project-URL: Homepage, https://github.com/fulkerson-advisors/agentic-context-engineering
Project-URL: Repository, https://github.com/fulkerson-advisors/agentic-context-engineering
Project-URL: Issues, https://github.com/fulkerson-advisors/agentic-context-engineering/issues
Author: PulseChk LLC
License: MIT
License-File: LICENSE
Keywords: agents,context,faiss,llm,openai
Classifier: Development Status :: 3 - Alpha
Classifier: Intended Audience :: Developers
Classifier: License :: OSI Approved :: MIT License
Classifier: Programming Language :: Python :: 3
Classifier: Programming Language :: Python :: 3.10
Classifier: Programming Language :: Python :: 3.11
Classifier: Programming Language :: Python :: 3.12
Classifier: Topic :: Scientific/Engineering :: Artificial Intelligence
Classifier: Topic :: Software Development :: Libraries
Requires-Python: >=3.10
Requires-Dist: faiss-cpu>=1.9.0
Requires-Dist: numpy>=1.26.4
Requires-Dist: openai-agents>=0.3.3
Requires-Dist: openai>=1.109.1
Requires-Dist: pydantic>=2.0.0
Requires-Dist: python-dotenv>=1.0.1
Provides-Extra: test
Requires-Dist: pytest>=8.0.0; extra == 'test'
